./.gitignore
./PKG-INFO
./README.md
./pyproject.toml
./vision_agents/plugins/smart_turn/__init__.py
./vision_agents/plugins/smart_turn/smart_turn_detection.py
vision_agents/plugins/smart_turn/__init__.py
vision_agents/plugins/smart_turn/smart_turn_detection.py
vision_agents_plugins_smart_turn-0.2.10.dist-info/METADATA
vision_agents_plugins_smart_turn-0.2.10.dist-info/WHEEL
vision_agents_plugins_smart_turn-0.2.10.dist-info/RECORD
