Metadata-Version: 2.4
Name: vision-agents-plugins-smart-turn
Version: 0.2.10
Summary: Smart Turn detection plugin for Vision Agents
Project-URL: Documentation, https://visionagents.ai/
Project-URL: Website, https://visionagents.ai/
Project-URL: Source, https://github.com/GetStream/Vision-Agents
License-Expression: MIT
Requires-Python: >=3.10
Requires-Dist: httpx>=0.27.0
Requires-Dist: numpy<2.3,>=2.2.6
Requires-Dist: onnxruntime>=1.20.1
Requires-Dist: transformers>=4.48.2
Requires-Dist: vision-agents
